adyen/__init__.py
adyen/admin.py
adyen/config.py
adyen/facade.py
adyen/gateway.py
adyen/models.py
adyen/scaffold.py
adyen/settings_config.py
adyen/migrations/0001_initial.py
adyen/migrations/0002_auto_20141016_1601.py
adyen/migrations/__init__.py
django_oscar_adyen-0.5.0.dist-info/DESCRIPTION.rst
django_oscar_adyen-0.5.0.dist-info/METADATA
django_oscar_adyen-0.5.0.dist-info/RECORD
django_oscar_adyen-0.5.0.dist-info/WHEEL
django_oscar_adyen-0.5.0.dist-info/metadata.json
django_oscar_adyen-0.5.0.dist-info/top_level.txt
tests/__init__.py
tests/settings.py
tests/test_adyen.py
tests/test_config.py
tests/test_notifications.py
tests/test_redirects.py
tests/test_requests.py
tests/test_unit_tests.py
