Metadata-Version: 2.0
Name: django-oscar-adyen
Version: 0.5.0
Summary: Adyen payment module for django-oscar
Home-page: https://github.com/oscaro/django-oscar-adyen
Author: Oscaro
Author-email: UNKNOWN
License: BSD
Keywords: payment,django,oscar,adyen
Platform: UNKNOWN
Classifier: Development Status :: 4 - Beta
Classifier: Environment :: Web Environment
Classifier: Framework :: Django
Classifier: Intended Audience :: Developers
Classifier: License :: OSI Approved :: BSD License
Classifier: Operating System :: POSIX :: Linux
Classifier: Programming Language :: Python
Classifier: Programming Language :: Python :: 3
Classifier: Programming Language :: Python :: 3.3
Classifier: Programming Language :: Python :: 3.4
Classifier: Topic :: Office/Business :: Financial :: Point-Of-Sale
Classifier: Topic :: Software Development :: Libraries :: Python Modules
Requires-Dist: iptools (==0.6.1)
Requires-Dist: requests (>=2.0,<3.0)
